mseep_basic_memory-1.0.0.dist-info/licenses/LICENSE
tests/__init__.py
tests/conftest.py
tests/test_config.py
tests/test_db_migration_deduplication.py
tests/markdown/__init__.py
tests/markdown/test_entity_parser.py
tests/markdown/test_markdown_plugins.py
tests/markdown/test_markdown_processor.py
tests/markdown/test_observation_edge_cases.py
tests/markdown/test_parser_edge_cases.py
tests/markdown/test_relation_edge_cases.py
tests/markdown/test_task_detection.py
mseep_basic_memory-1.0.0.dist-info/METADATA
mseep_basic_memory-1.0.0.dist-info/WHEEL
mseep_basic_memory-1.0.0.dist-info/top_level.txt
mseep_basic_memory-1.0.0.dist-info/RECORD
