Metadata-Version: 2.4
Name: mseep-basic-memory
Version: 1.0.0
Summary: Local-first knowledge management combining Zettelkasten with knowledge graphs
Home-page: https://github.com/mseep
Author: mseep
Author-email: support@skydeck.ai
Maintainer: mseep
Maintainer-email: support@skydeck.ai
Keywords: mseep
Classifier: Programming Language :: Python :: 3
Classifier: License :: OSI Approved :: MIT License
Classifier: Operating System :: OS Independent
Requires-Python: >=3.6
License-File: LICENSE
Requires-Dist: sqlalchemy>=2.0.0
Requires-Dist: pyyaml>=6.0.1
Requires-Dist: typer>=0.9.0
Requires-Dist: aiosqlite>=0.20.0
Requires-Dist: greenlet>=3.1.1
Requires-Dist: pydantic[email,timezone]>=2.10.3
Requires-Dist: icecream>=2.1.3
Requires-Dist: mcp>=1.2.0
Requires-Dist: pydantic-settings>=2.6.1
Requires-Dist: loguru>=0.7.3
Requires-Dist: pyright>=1.1.390
Requires-Dist: markdown-it-py>=3.0.0
Requires-Dist: python-frontmatter>=1.1.0
Requires-Dist: rich>=13.9.4
Requires-Dist: unidecode>=1.3.8
Requires-Dist: dateparser>=1.2.0
Requires-Dist: watchfiles>=1.0.4
Requires-Dist: fastapi[standard]>=0.115.8
Requires-Dist: alembic>=1.14.1
Requires-Dist: pillow>=11.1.0
Requires-Dist: pybars3>=0.9.7
Requires-Dist: fastmcp==2.10.2
Requires-Dist: pyjwt>=2.10.1
Requires-Dist: python-dotenv>=1.1.0
Requires-Dist: pytest-aio>=1.9.0
Dynamic: author
Dynamic: author-email
Dynamic: classifier
Dynamic: description
Dynamic: description-content-type
Dynamic: home-page
Dynamic: keywords
Dynamic: license-file
Dynamic: maintainer
Dynamic: maintainer-email
Dynamic: requires-dist
Dynamic: requires-python
Dynamic: summary
